package/__init__.py
package/main.py
hello_sijey-1.0.0.dist-info/LICENSE
hello_sijey-1.0.0.dist-info/METADATA
hello_sijey-1.0.0.dist-info/WHEEL
hello_sijey-1.0.0.dist-info/top_level.txt
hello_sijey-1.0.0.dist-info/RECORD
