Metadata-Version: 2.1
Name: hello_sijey
Version: 1.0.0
Summary: This is my first module!
Home-page: https://t.me/sijeydev
Author: sijeydev
Author-email: sijeydev@gmail.com
Project-URL: Documentation, https://t.me/sijeydev
Keywords: sijeydev sijey
Classifier: Programming Language :: Python :: 3.11
Classifier: License :: OSI Approved :: MIT License
Classifier: Operating System :: OS Independent
Requires-Python: >=3.7
License-File: LICENSE
Requires-Dist: requests>=2.25.1
